kavahq
tests
