Metadata-Version: 1.1
Name: kavahq-api
Version: 0.2.13
Summary: wrapper over kavahq.com API
Home-page: https://github.com/42cc/apiclient-kava
Author: 42 Coffee Cups
Author-email: contact@42cc.co
License: GPL v2 License
Download-URL: https://github.com/42cc/apiclient-kava/archive/master.zip
Keywords: kavahq,api
Platform: UNKNOWN
Classifier: Environment :: Web Environment
Classifier: Intended Audience :: Developers
Classifier: License :: OSI Approved :: GNU General Public License v2 (GPLv2)
Classifier: Programming Language :: Python
Requires: python (>= 2.7)
